fast_langdetect-1.0.0.dist-info/METADATA
fast_langdetect-1.0.0.dist-info/WHEEL
fast_langdetect-1.0.0.dist-info/entry_points.txt
fast_langdetect-1.0.0.dist-info/licenses/LICENSE
fast_langdetect-1.0.0.dist-info/licenses/NOTICE.MD
fast_langdetect/LICENSE
fast_langdetect/__init__.py
fast_langdetect/infer.py
fast_langdetect/resources/NOTICE.MD
fast_langdetect/resources/lid.176.ftz
fast_langdetect-1.0.0.dist-info/RECORD
