Metadata-Version: 2.1
Name: fast-langdetect
Version: 1.0.0
Summary: Quickly detect text language and segment language
Author-Email: sudoskys <coldlando@hotmail.com>
License: MIT
Requires-Python: >=3.9
Requires-Dist: robust-downloader>=0.0.2
Requires-Dist: requests>=2.32.3
Requires-Dist: fasttext-predict>=0.9.2.4
